setup.py
buildstack/__init__.py
buildstack/__main__.py
buildstack/ansible.py
buildstack/ant.py
buildstack/autotools.py
buildstack/bower.py
buildstack/buck.py
buildstack/builtin.py
buildstack/cargo.py
buildstack/cmake.py
buildstack/gradle.py
buildstack/grunt.py
buildstack/gulp.py
buildstack/jam.py
buildstack/maven.py
buildstack/msbuild.py
buildstack/nant.py
buildstack/ninja.py
buildstack/npm.py
buildstack/rake.py
buildstack/scons.py
buildstack/setuptools.py
buildstack/shake.py
buildstack/stack.py
buildstack/tup.py
buildstack/universe.py
buildstack/vagrant.py
buildstack.egg-info/PKG-INFO
buildstack.egg-info/SOURCES.txt
buildstack.egg-info/dependency_links.txt
buildstack.egg-info/entry_points.txt
buildstack.egg-info/requires.txt
buildstack.egg-info/top_level.txt