Metadata-Version: 1.0
Name: buildstack
Version: 6.3.0
Summary: Build stack wrapper
Home-page: https://github.com/fclaerho/buildstack
Author: florent claerhout
Author-email: code@fclaerhout.fr
License: MIT
Platform: UNKNOWN
